glidergun/__init__.py
glidergun/_display.py
glidergun/_focal.py
glidergun/_geojson.py
glidergun/_grid.py
glidergun/_interpolation.py
glidergun/_literals.py
glidergun/_mosaic.py
glidergun/_quadkey.py
glidergun/_sam.py
glidergun/_stac.py
glidergun/_stack.py
glidergun/_types.py
glidergun/_utils.py
glidergun/_zonal.py
glidergun/assets/bpe_simple_vocab_16e6.txt.gz
glidergun-0.9.36.dist-info/licenses/LICENSE
glidergun-0.9.36.dist-info/METADATA
glidergun-0.9.36.dist-info/WHEEL
glidergun-0.9.36.dist-info/top_level.txt
glidergun-0.9.36.dist-info/RECORD
