Metadata-Version: 2.4
Name: glidergun
Version: 0.9.36
Summary: Map Algebra with NumPy
License-Expression: MIT
Project-URL: Homepage, https://github.com/jshirota/glidergun
Project-URL: Bug Tracker, https://github.com/jshirota/glidergun/issues
Requires-Python: >=3.10
License-File: LICENSE
Requires-Dist: ipython>=8.0.0
Requires-Dist: matplotlib>=3.5.1
Requires-Dist: numpy>=1.22.0
Requires-Dist: planetary-computer>=1.0.0
Requires-Dist: rasterio>=1.2.10
Requires-Dist: scikit-learn>=1.0.2
Requires-Dist: scipy>=1.7.3
Requires-Dist: shapely>=1.8.0
Dynamic: license-file
